quantum_mcp/__init__.py
quantum_mcp/server.py
scicomp_quantum_mcp-0.1.6.dist-info/METADATA
scicomp_quantum_mcp-0.1.6.dist-info/WHEEL
scicomp_quantum_mcp-0.1.6.dist-info/entry_points.txt
scicomp_quantum_mcp-0.1.6.dist-info/RECORD
